tmla/__init__.py
tmla/config.py
tmla/tcm.py
tmla/attacks/__init__.py
tmla/attacks/metrics.py
tmla/attacks/multiscale.py
tmla/attacks/multiscale_decomp.py
tmla/attacks/reconstruct.py
tmla/utils/__init__.py
tmla/utils/device_utils.py
tmla/utils/eval_utils.py
tmla/utils/file_utils.py
tmla/utils/image_utils.py
tmla/utils/preprocessing.py
tmla-0.1.1.dist-info/licenses/LICENSE
tmla-0.1.1.dist-info/METADATA
tmla-0.1.1.dist-info/WHEEL
tmla-0.1.1.dist-info/top_level.txt
tmla-0.1.1.dist-info/RECORD
