Metadata-Version: 2.4
Name: tmla
Version: 0.1.1
Summary: T-MLA: Targeted Multiscale Log-Exponential Attack for Neural Image Compression
Author-email: "N. I. Kalmykov" <nikolay.kalmykov@skoltech.ru>
License-Expression: MIT
Keywords: adversarial attacks,neural image compression,frequency-domain analysis,ai safety
Classifier: Development Status :: 4 - Beta
Classifier: Intended Audience :: Science/Research
Classifier: Programming Language :: Python :: 3
Classifier: Programming Language :: Python :: 3.10
Classifier: Programming Language :: Python :: 3.11
Classifier: Topic :: Scientific/Engineering
Requires-Python: >=3.10
License-File: LICENSE
Requires-Dist: torch>=2.0
Requires-Dist: torchvision
Requires-Dist: compressai>=1.2
Requires-Dist: kornia>=0.6
Requires-Dist: piq>=0.7
Requires-Dist: pytorch-wavelets>=1.3
Requires-Dist: torchmetrics>=1.0
Requires-Dist: numpy
Requires-Dist: pillow
Requires-Dist: scikit-image
Requires-Dist: matplotlib
Requires-Dist: pandas
Requires-Dist: gdown
Requires-Dist: kagglehub
Provides-Extra: dev
Requires-Dist: pytest; extra == "dev"
Requires-Dist: black; extra == "dev"
Requires-Dist: ruff; extra == "dev"
Dynamic: license-file
